LICENSE
README.md
setup.py
luarine.egg-info/PKG-INFO
luarine.egg-info/SOURCES.txt
luarine.egg-info/dependency_links.txt
luarine.egg-info/top_level.txt
lunarine/__init__.py
lunarine/_client.py
lunarine/_connector.py
lunarine/_main.py
lunarine/_model.py