Metadata-Version: 2.1
Name: luarine
Version: 0.1
Summary: Lunar Client local api wrapper for Python
Home-page: https://github.com/voids-top/lunarine
Author: NaeCqde
License: MIT
Keywords: python lunarclient api
License-File: LICENSE
